hitcounter/__init__.py
hitcounter/hitcounter.py
hitcounter-0.2.dist-info/METADATA
hitcounter-0.2.dist-info/WHEEL
hitcounter-0.2.dist-info/top_level.txt
hitcounter-0.2.dist-info/RECORD
